{
  "build": {

    "content": [
      {
        "files": [
          "**/*.md",
          "**/*.yml"
        ],
        "exclude": [
          "**/obj/**",
          "**/includes/**",
          "_themes/**",
          "_themes.pdf/**",
          "**/docfx.json",
          "_repo.en-us/**",
          "README.md",
          "LICENSE",
          "LICENSE-CODE",
          "ThirdPartyNotices.md"
        ]
      }
    ],

    "resource": [
      {
        "files": [
          "**/*.svg",
          "**/*.png",
          "**/*.jpg",
          "**/*.jpeg",
          "**/*.gif"
        ],
        "exclude": [
          "**/obj/**",
          "**/includes/**",
          "_themes/**",
          "_themes.pdf/**",
          "**/docfx.json",
          "_repo.en-us/**"
        ]
      }
    ],

    "overwrite": [],
    "externalReference": [],

    "globalMetadata": {
      "breadcrumb_path": "/support/breadcrumb/toc.json",
      "extendBreadcrumb": true,
      "feedback_system": "None"
    },

    "fileMetadata": {

      "layout":{
        "**/index.yml": "LandingPage"
      },

      "manager": {
        "**/*.md": "dcscontentpm"
      },
      "audience": {
        "**/*.md": "itpro"
      },
      "author": {
        "**/*.md": "ramakoni1"
      },
      "ms.author": {
        "**/*.md": "ramakoni"
      },
      "ms.localizationpriority": {
        "**/*.md": "Normal"
      },
      "ms.reviewer": {
        "**/*.md": "DEV_Triage, DaleChe, RamaKoni, DelHan, SureshKa, SueHar"
      },
      "ms.topic": {
        "**/*.md": "troubleshooting"
      },

      "ms.prod": {
        "biztalk/**/*.md": "biztalk-server"
      },
      "ms.technology": {
        "biztalk/**/*.md": ""
      },

      "ms.prod": {
        "dotnet/**/*.md": ".net"
      },
      "ms.technology": {
        "dotnet/**/*.md": ""
      },

      "ms.prod": {
        "visualstudio/**/*.md": "visual-studio-family"
      },
      "ms.technology": {
        "visualstudio/**/*.md": ""
      },

      "ms.prod": {
        "webapps/**/*.md": "web-apps-server"
      },
      "ms.technology": {
        "webapps/**/*.md": ""
      },

      "ms.prod": {
        "windowsdeveloper/**/*.md": "windows-dev-apps"
      },
      "ms.technology": {
        "windowsdeveloper/**/*.md": ""
      },

      "ms.prod": {
        "mem/intune/**/*.md": "intune"
      },
      "ms.technology": {
        "mem/intune/**/*.md": "microsoft-graph"
      },

      "titleSuffix": {
        "biztalk/**/*.md": "BizTalk Server"
      },      
      "titleSuffix": {
        "dotnet/**/*.md": ".NET"
      },
      "titleSuffix": {
        "aspnet/**/*.md": "ASP.NET"
      },
      "titleSuffix": {
        "visualstudio/**/*.md": "Visual Studio"
      },
      "titleSuffix": {
        "cpp/**/*.md": "Visual C++"
      },
      "titleSuffix": {
        "iis/**/*.md": "Internet Information Services"
      },
      "titleSuffix": {
        "webapps/**/*.md": "Web Apps"
      },
      "titleSuffix": {
        "windows/win32/**/*.md": "Windows Developer"
      },
      "titleSuffix": {
        "mem/intune/**/*.md": "Intune"
      }
    },

    "template": [],
    "dest": "support1-docset",
    "markdownEngineName": "markdig"

  }
}
